karabind/__init__.py
karabo_cpp/VERSION
karabo_cpp/bin/karabo-brokermessagelogger
karabo_cpp/bin/karabo-brokerrates
karabo_cpp/bin/karabo-cppserver
karabo_cpp/bin/karabo-idxbuild
karabo_cpp/bin/karabo-idxview
karabo_cpp/extern/lib/libamqpcpp.so
karabo_cpp/extern/lib/libamqpcpp.so.4.3
karabo_cpp/extern/lib/libbacktrace.so
karabo_cpp/extern/lib/libbacktrace.so.0
karabo_cpp/extern/lib/libbacktrace.so.0.0.0
karabo_cpp/extern/lib/libboost_atomic.so
karabo_cpp/extern/lib/libboost_atomic.so.1.85.0
karabo_cpp/extern/lib/libboost_charconv.so
karabo_cpp/extern/lib/libboost_charconv.so.1.85.0
karabo_cpp/extern/lib/libboost_chrono.so
karabo_cpp/extern/lib/libboost_chrono.so.1.85.0
karabo_cpp/extern/lib/libboost_container.so
karabo_cpp/extern/lib/libboost_container.so.1.85.0
karabo_cpp/extern/lib/libboost_context.so
karabo_cpp/extern/lib/libboost_context.so.1.85.0
karabo_cpp/extern/lib/libboost_contract.so
karabo_cpp/extern/lib/libboost_contract.so.1.85.0
karabo_cpp/extern/lib/libboost_date_time.so
karabo_cpp/extern/lib/libboost_date_time.so.1.85.0
karabo_cpp/extern/lib/libboost_exception.a
karabo_cpp/extern/lib/libboost_filesystem.so
karabo_cpp/extern/lib/libboost_filesystem.so.1.85.0
karabo_cpp/extern/lib/libboost_iostreams.so
karabo_cpp/extern/lib/libboost_iostreams.so.1.85.0
karabo_cpp/extern/lib/libboost_json.so
karabo_cpp/extern/lib/libboost_json.so.1.85.0
karabo_cpp/extern/lib/libboost_locale.so
karabo_cpp/extern/lib/libboost_locale.so.1.85.0
karabo_cpp/extern/lib/libboost_log.so
karabo_cpp/extern/lib/libboost_log.so.1.85.0
karabo_cpp/extern/lib/libboost_log_setup.so
karabo_cpp/extern/lib/libboost_log_setup.so.1.85.0
karabo_cpp/extern/lib/libboost_nowide.so
karabo_cpp/extern/lib/libboost_nowide.so.1.85.0
karabo_cpp/extern/lib/libboost_program_options.so
karabo_cpp/extern/lib/libboost_program_options.so.1.85.0
karabo_cpp/extern/lib/libboost_random.so
karabo_cpp/extern/lib/libboost_random.so.1.85.0
karabo_cpp-2.21.4.dist-info/METADATA
karabo_cpp-2.21.4.dist-info/WHEEL
karabo_cpp-2.21.4.dist-info/entry_points.txt
karabo_cpp-2.21.4.dist-info/RECORD
