Metadata-Version: 2.4
Name: karabo.cpp
Version: 2.21.4
Summary: Karabo's C++ API and Python bindings thereof
Keywords: Karabo,SCADA,async,control system
Author-Email: European XFEL GmbH <opensource@xfel.eu>
Maintainer-Email: "S. Hauf" <steffen.hauf@xfel.eu>, "D. Goeries" <dennis.goeries@xfel.eu>
License-Expression: MPL-2.0
Classifier: Development Status :: 5 - Production/Stable
Classifier: Intended Audience :: Developers
Classifier: Intended Audience :: Science/Research
Project-URL: Homepage, https://github.com/European-XFEL/Karabo
Project-URL: Bug Reports, https://github.com/European-XFEL/Karabo/issues
Project-URL: Source, https://github.com/European-XFEL/Karabo
Requires-Python: ==3.12.*
Requires-Dist: karabo-native==2.21.4
